src/__init__.py
src/data/__init__.py
src/data/make_dataset.py
src/data/masked_lm_tse_dataset.py
src/data/token_classification_tse_dataset.py
src/models/__init__.py
src/models/distillbert_masked_lm_train.py
src/models/distillbert_tokens_classification_train.py
src/models/utils.py
tweet_se_competition-0.5.0.dist-info/LICENSE
tweet_se_competition-0.5.0.dist-info/METADATA
tweet_se_competition-0.5.0.dist-info/WHEEL
tweet_se_competition-0.5.0.dist-info/entry_points.txt
tweet_se_competition-0.5.0.dist-info/top_level.txt
tweet_se_competition-0.5.0.dist-info/RECORD
