Metadata-Version: 2.1
Name: tweet-se-competition
Version: 0.5.0
Summary: a machine learning project for kaggle tweet sentiment extraction competition
Home-page: UNKNOWN
Author: Simon Meoni
Author-email: UNKNOWN
License: MIT
Platform: UNKNOWN
Requires-Dist: click (==7.1.2)
Requires-Dist: pandas (==1.2.0)
Requires-Dist: python-dotenv (==0.15.0)
Requires-Dist: tokenizers (==0.9.4)
Requires-Dist: torch (==1.7.1)
Requires-Dist: tqdm (==4.56.0)
Requires-Dist: wandb (==0.10.14)
Requires-Dist: numpy (==1.19.5)
Requires-Dist: sklearn (==0.0)
Requires-Dist: scikit-learn (==0.24.0)
Requires-Dist: transformers (==4.2.1)
